{"http_code":200,"body":{"id":"MLB4277314697","site_id":"MLB","title":"Lixeira Inox 4l Suspensa Premium - Cozinha Banheiro Bancada Prateado","family_name":"Lixeira Inox 4l Suspensa Premium - Cozinha Banheiro Bancada","family_id":2109681798496445,"seller_id":2644279415,"category_id":"MLB33375","user_product_id":"MLBU3524738140","official_store_id":null,"price":279,"base_price":279,"original_price":null,"inventory_id":null,"currency_id":"BRL","initial_quantity":25,"available_quantity":25,"sold_quantity":0,"sale_terms":[{"id":"WARRANTY_TYPE","name":"Tipo de garantia","value_id":"2230280","value_name":"Garantia do vendedor","value_struct":null,"values":[{"id":"2230280","name":"Garantia do vendedor","struct":null}],"value_type":"list"},{"id":"WARRANTY_TIME","name":"Tempo de garantia","value_id":null,"value_name":"90 dias","value_struct":{"number":90,"unit":"dias"},"values":[{"id":null,"name":"90 dias","struct":{"number":90,"unit":"dias"}}],"value_type":"number_unit"}],"buying_mode":"buy_it_now","listing_type_id":"gold_pro","start_time":"2025-10-28T14:46:34.222Z","stop_time":"2045-10-23T04:00:00.000Z","end_time":"2045-10-23T04:00:00.000Z","expiration_time":"2026-02-04T22:47:01.136Z","condition":"new","permalink":"https:\/\/produto.mercadolivre.com.br\/MLB-4277314697-lixeira-inox-4l-suspensa-premium-cozinha-banheiro-bancada-prateado-_JM","thumbnail_id":"958574-MLB96504477519_102025","thumbnail":"http:\/\/http2.mlstatic.com\/D_958574-MLB96504477519_102025-I.jpg","pictures":[{"id":"958574-MLB96504477519_102025","url":"http:\/\/http2.mlstatic.com\/D_958574-MLB96504477519_102025-O.jpg","secure_url":"https:\/\/http2.mlstatic.com\/D_958574-MLB96504477519_102025-O.jpg","size":"400x500","max_size":"960x1200","quality":""},{"id":"654124-MLB96503911173_102025","url":"http:\/\/http2.mlstatic.com\/D_654124-MLB96503911173_102025-O.jpg","secure_url":"https:\/\/http2.mlstatic.com\/D_654124-MLB96503911173_102025-O.jpg","size":"500x500","max_size":"1200x1200","quality":""},{"id":"605116-MLB96503961131_102025","url":"http:\/\/http2.mlstatic.com\/D_605116-MLB96503961131_102025-O.jpg","secure_url":"https:\/\/http2.mlstatic.com\/D_605116-MLB96503961131_102025-O.jpg","size":"371x500","max_size":"891x1200","quality":""},{"id":"910469-MLB96504407787_102025","url":"http:\/\/http2.mlstatic.com\/D_910469-MLB96504407787_102025-O.jpg","secure_url":"https:\/\/http2.mlstatic.com\/D_910469-MLB96504407787_102025-O.jpg","size":"431x500","max_size":"1035x1200","quality":""},{"id":"874561-MLB96504546653_102025","url":"http:\/\/http2.mlstatic.com\/D_874561-MLB96504546653_102025-O.jpg","secure_url":"https:\/\/http2.mlstatic.com\/D_874561-MLB96504546653_102025-O.jpg","size":"400x500","max_size":"960x1200","quality":""},{"id":"843450-MLB96504020869_102025","url":"http:\/\/http2.mlstatic.com\/D_843450-MLB96504020869_102025-O.jpg","secure_url":"https:\/\/http2.mlstatic.com\/D_843450-MLB96504020869_102025-O.jpg","size":"481x500","max_size":"928x963","quality":""},{"id":"664377-MLB96061054858_102025","url":"http:\/\/http2.mlstatic.com\/D_664377-MLB96061054858_102025-O.jpg","secure_url":"https:\/\/http2.mlstatic.com\/D_664377-MLB96061054858_102025-O.jpg","size":"402x500","max_size":"818x1015","quality":""}],"video_id":null,"descriptions":[],"accepts_mercadopago":true,"non_mercado_pago_payment_methods":[],"shipping":{"mode":"me2","methods":[],"tags":["mandatory_free_shipping"],"dimensions":null,"local_pick_up":false,"free_shipping":true,"logistic_type":"drop_off","store_pick_up":false},"international_delivery_mode":"none","seller_address":{"comment":"Referencia: Condom\u00ednio Serra da Estrela","address_line":"Alameda Rouxinol 165","zip_code":"12945746","city":{"id":"BR-SP-56","name":"Atibaia"},"state":{"id":"BR-SP","name":"S\u00e3o Paulo"},"country":{"id":"BR","name":"Brasil"},"search_location":{"neighborhood":{"id":"TVhYQ29uZG9tw61uaW8gU2VycmEgRGEgRXN0c","name":"Condom\u00ednio Serra Da Estrela"},"city":{"id":"TVhYQXRpYmFpYVRVeENVRk5CVDA4NU4yRTQ","name":"Atibaia"},"state":{"id":"TUxCUFNBT085N2E4","name":"S\u00e3o Paulo"}},"latitude":-23.106991,"longitude":-46.488174,"id":1514532410},"seller_contact":null,"location":[],"geolocation":{"latitude":-23.106991,"longitude":-46.488174},"coverage_areas":[],"attributes":[{"id":"BRAND","name":"Marca","value_id":"63643221","value_name":"OrgaHome","values":[{"id":"63643221","name":"OrgaHome","struct":null}],"value_type":"string"},{"id":"COLOR","name":"Cor","value_id":"52053","value_name":"Prateado","values":[{"id":"52053","name":"Prateado","struct":null}],"value_type":"string"},{"id":"CONAMA_LICENSE_NUMBER","name":"N\u00famero de licen\u00e7a do CONAMA","value_id":"-1","value_name":null,"values":[{"id":"-1","name":null,"struct":null}],"value_type":"string"},{"id":"GTIN","name":"C\u00f3digo universal de produto","value_id":null,"value_name":"7893705476408","values":[{"id":null,"name":"7893705476408","struct":null}],"value_type":"string"},{"id":"HEIGHT","name":"Altura","value_id":null,"value_name":"24 cm","values":[{"id":null,"name":"24 cm","struct":{"number":24,"unit":"cm"}}],"value_type":"number_unit"},{"id":"INSTALLATION_PLACEMENT","name":"Lugar de coloca\u00e7\u00e3o","value_id":"37365627","value_name":"Suspensa","values":[{"id":"37365627","name":"Suspensa","struct":null}],"value_type":"string"},{"id":"IS_BUILT_IN","name":"\u00c9 de embutir","value_id":"242085","value_name":"Sim","values":[{"id":"242085","name":"Sim","struct":null}],"value_type":"boolean"},{"id":"ITEM_CONDITION","name":"Condi\u00e7\u00e3o do item","value_id":"2230284","value_name":"Novo","values":[{"id":"2230284","name":"Novo","struct":null}],"value_type":"list"},{"id":"LENGTH","name":"Comprimento","value_id":null,"value_name":"17 cm","values":[{"id":null,"name":"17 cm","struct":{"number":17,"unit":"cm"}}],"value_type":"number_unit"},{"id":"LID_MATERIAL","name":"Material da tampa","value_id":"20906694","value_name":"Inox","values":[{"id":"20906694","name":"Inox","struct":null}],"value_type":"string"},{"id":"MAIN_COLOR","name":"Cor principal","value_id":"2450303","value_name":"Prateado","values":[{"id":"2450303","name":"Prateado","struct":null}],"value_type":"list"},{"id":"MODEL","name":"Modelo","value_id":"65340677","value_name":"Lixeira 4L","values":[{"id":"65340677","name":"Lixeira 4L","struct":null}],"value_type":"string"},{"id":"SALE_FORMAT","name":"Formato de venda","value_id":"1359391","value_name":"Unidade","values":[{"id":"1359391","name":"Unidade","struct":null}],"value_type":"list"},{"id":"SELLER_PACKAGE_HEIGHT","name":"Altura da embalagem do vendor","value_id":null,"value_name":"39 cm","values":[{"id":null,"name":"39 cm","struct":{"number":39,"unit":"cm"}}],"value_type":"number_unit"},{"id":"SELLER_PACKAGE_LENGTH","name":"Comprimento da embalagem do vendor","value_id":null,"value_name":"24 cm","values":[{"id":null,"name":"24 cm","struct":{"number":24,"unit":"cm"}}],"value_type":"number_unit"},{"id":"SELLER_PACKAGE_TYPE","name":"Tipo da embalagem do vendor","value_id":"47115156","value_name":"Com embalagem adicional","values":[{"id":"47115156","name":"Com embalagem adicional","struct":null}],"value_type":"list"},{"id":"SELLER_PACKAGE_WEIGHT","name":"Peso da embalagem do vendor","value_id":null,"value_name":"1775 g","values":[{"id":null,"name":"1775 g","struct":{"number":1775,"unit":"g"}}],"value_type":"number_unit"},{"id":"SELLER_PACKAGE_WIDTH","name":"Largura da embalagem do vendor","value_id":null,"value_name":"29 cm","values":[{"id":null,"name":"29 cm","struct":{"number":29,"unit":"cm"}}],"value_type":"number_unit"},{"id":"STRUCTURE_MATERIALS","name":"Materiais da estrutura","value_id":"13126484","value_name":"Inox","values":[{"id":"13126484","name":"Inox","struct":null}],"value_type":"string"},{"id":"UNITS_PER_PACK","name":"Unidades por kit","value_id":null,"value_name":"1","values":[{"id":null,"name":"1","struct":null}],"value_type":"number"},{"id":"VOLUME_CAPACITY","name":"Capacidade em volume","value_id":null,"value_name":"4 L","values":[{"id":null,"name":"4 L","struct":{"number":4,"unit":"L"}}],"value_type":"number_unit"},{"id":"WASTE_BASKET_OPENING_TYPES","name":"Tipos de aberturas","value_id":"17708855","value_name":"Manual","values":[{"id":"17708855","name":"Manual","struct":null}],"value_type":"string"},{"id":"WEIGHT","name":"Peso","value_id":null,"value_name":"800 g","values":[{"id":null,"name":"800 g","struct":{"number":800,"unit":"g"}}],"value_type":"number_unit"},{"id":"WIDTH","name":"Largura","value_id":null,"value_name":"12 cm","values":[{"id":null,"name":"12 cm","struct":{"number":12,"unit":"cm"}}],"value_type":"number_unit"}],"warnings":[],"listing_source":"","variations":[],"status":"active","sub_status":[],"tags":["user_product_listing","good_quality_thumbnail","immediate_payment","cart_eligible"],"warranty":"Garantia do vendedor: 90 dias","catalog_product_id":null,"domain_id":"MLB-WASTE_BASKETS","seller_custom_field":null,"parent_item_id":null,"differential_pricing":null,"deal_ids":[],"automatic_relist":false,"date_created":"2025-10-28T14:46:34.382Z","last_updated":"2025-11-16T22:47:01.158Z","health":null,"catalog_listing":false,"item_relations":[],"channels":["marketplace"]}}